langchain_falkordb/__init__.py
langchain_falkordb/message_history.py
langchain_falkordb/vectorstores.py
langchain_falkordb-0.1.2.dist-info/METADATA
langchain_falkordb-0.1.2.dist-info/WHEEL
langchain_falkordb-0.1.2.dist-info/RECORD
