Metadata-Version: 2.1
Name: langchain-falkordb
Version: 0.1.2
Summary: 
Author: kingtroga
Author-email: trogaclassicman@gmail.com
Requires-Python: >=3.9,<4.0
Classifier: Programming Language :: Python :: 3
Classifier: Programming Language :: Python :: 3.9
Classifier: Programming Language :: Python :: 3.10
Classifier: Programming Language :: Python :: 3.11
Classifier: Programming Language :: Python :: 3.12
Classifier: Programming Language :: Python :: 3.13
Requires-Dist: falkordb (>=1.0.10,<2.0.0)
Requires-Dist: langchain-community (>=0.3.9,<0.4.0)
Requires-Dist: langchain-core (>=0.3.21,<0.4.0)
